ctreepo/__init__.py
ctreepo/ctree.py
ctreepo/differ.py
ctreepo/environment.py
ctreepo/factory.py
ctreepo/models.py
ctreepo/parser.py
ctreepo/postproc.py
ctreepo/postproc_arista.py
ctreepo/postproc_cisco.py
ctreepo/postproc_fortinet.py
ctreepo/postproc_huawei.py
ctreepo/py.typed
ctreepo/searcher.py
ctreepo/serializer.py
ctreepo/settings.py
ctreepo/vendors.py
ctreepo-0.3.31.dist-info/METADATA
ctreepo-0.3.31.dist-info/WHEEL
ctreepo-0.3.31.dist-info/licenses/LICENSE
ctreepo-0.3.31.dist-info/RECORD
