Metadata-Version: 2.4
Name: ctreepo
Version: 0.3.31
Summary: CTreePO - configuration tree patch overview - Parsing, filtering and diff calculation for network device configurations
License-Expression: Apache-2.0
License-File: LICENSE
Keywords: cisco,arista,huawei,network,automation,configuration
Author: Alexander Ignatov
Author-email: alexigna@ozon.ru
Requires-Python: >=3.11
Classifier: Programming Language :: Python :: 3
Classifier: Programming Language :: Python :: 3.11
Classifier: Programming Language :: Python :: 3.12
Classifier: Programming Language :: Python :: 3.13
Classifier: Programming Language :: Python :: 3.14
Requires-Dist: pyyaml (>=6.0)
